siogeen/tools/IoddComChecker.cpython-314-x86_64-linux-gnu.so
siogeen/tools/__init__.py
siogeen/tools/cli/IoddComChecker.py
siogeen/tools/cli/__init__.py
ioddcomchecker-1.9.0.dist-info/METADATA
ioddcomchecker-1.9.0.dist-info/WHEEL
ioddcomchecker-1.9.0.dist-info/top_level.txt
ioddcomchecker-1.9.0.dist-info/RECORD
ioddcomchecker-1.9.0.dist-info/licenses/LICENSE.txt
