Metadata-Version: 2.4
Name: ioddcomchecker
Version: 1.9.0
Summary: IoddCom IO-Link master checker
Home-page: https://siogeen.com
Author: Reimund Renner
Author-email: reimund@siogeen.com
License: proprietary and confidential
Project-URL: Documentation, https://siogeen.com/doc/
Project-URL: Help Desk, https://siogeen.com/helpdesk/
Project-URL: Knowledge Base, https://siogeen.com/helpdesk/knowledgebase
Project-URL: News, https://news.siogeen.com/
Keywords: IO-Link,IODD,development,test,production
Classifier: Development Status :: 5 - Production/Stable
Classifier: Intended Audience :: Developers
Classifier: Intended Audience :: Manufacturing
Classifier: Intended Audience :: Science/Research
Classifier: Intended Audience :: Customer Service
Classifier: Topic :: Software Development :: Embedded Systems
Classifier: Topic :: Software Development :: Quality Assurance
Classifier: Topic :: Software Development :: Testing
Classifier: Operating System :: Microsoft :: Windows
Classifier: Operating System :: POSIX :: Linux
Classifier: Operating System :: MacOS :: MacOS X
Classifier: License :: Other/Proprietary License
Classifier: Programming Language :: Python :: 3.9
Classifier: Programming Language :: Python :: 3.10
Classifier: Programming Language :: Python :: 3.11
Classifier: Programming Language :: Python :: 3.12
Classifier: Programming Language :: Python :: 3.13
Classifier: Programming Language :: Python :: 3.14
Requires-Python: >=3.9
Requires-Dist: ioddcombase>=1.9.0
Requires-Dist: dict2obj>=1.2.0
Dynamic: author
Dynamic: author-email
Dynamic: classifier
Dynamic: description
Dynamic: description-content-type
Dynamic: home-page
Dynamic: keywords
Dynamic: license
Dynamic: project-url
Dynamic: requires-dist
Dynamic: requires-python
Dynamic: summary
